sibal/__init__.py
sibal/hell_symphony.wav
sibal-1.0.0.dist-info/licenses/LICENSE
sibal-1.0.0.dist-info/METADATA
sibal-1.0.0.dist-info/WHEEL
sibal-1.0.0.dist-info/top_level.txt
sibal-1.0.0.dist-info/RECORD
