Metadata-Version: 2.4
Name: sibal
Version: 1.0.0
Summary: A package that turns Python errors into a state of emergency with rainbow terminal madness and siren sounds.
Author-email: "Rheehose (Rhee Creative)" <rheehose@rheehose.com>
License: MIT
Project-URL: Homepage, https://rheehose.com
Classifier: Programming Language :: Python :: 3
Classifier: License :: OSI Approved :: MIT License
Classifier: Operating System :: OS Independent
Requires-Python: >=3.7
License-File: LICENSE
Dynamic: license-file
